<?xml version="1.0" encoding="UTF-8"?>
<pages><page><para height="17.28" id="70001" poly="m 108.9353 35.036034 l 108.9353 52.316 l 518.8553 52.316 l 518.8553 35.036034 z" width="409.92" x="108.935" y="35.036"><line height="27.504" id="70001" y="56.924"><word id="70001" width="66" x="108.935"><![CDATA[GENRE]]></word><word id="70002" width="68.688" x="183.551"><![CDATA[STUDY]]></word><word id="70003" width="13.536" x="260.855"><![CDATA[3]]></word><word id="70004" width="174.384" x="283.007"><![CDATA[ARGUMENTATIVE]]></word><word id="70005" width="53.112" x="465.983"><![CDATA[TEXT]]></word></line></para><para height="9.361" id="70002" poly="m 117.2001 76.68898 l 117.2001 86.05 l 532.8893 86.05 l 532.8893 76.68898 z" width="415.689" x="117.2" y="76.689"><line height="14.317" id="70002" y="89.04"><word id="70006" width="49.14" x="117.2"><![CDATA[Essential]]></word><word id="70007" width="49.91" x="170.79"><![CDATA[Question]]></word><word id="70008" width="312.839" x="221.361"><![CDATA[........................................................................................................................60]]></word></line></para><para height="9.217" id="70003" poly="m 121.5946 93.83302 l 121.5946 103.05 l 532.4984 103.05 l 532.4984 93.83302 z" width="410.904" x="121.595" y="93.833"><line height="16.068" id="70003" y="106.3"><word id="70009" width="61.815" x="229.317"><![CDATA[“Preserve]]></word><word id="70010" width="23.582" x="296.163"><![CDATA[and]]></word><word id="70011" width="54.002" x="324.776"><![CDATA[Protect”]]></word><word id="70012" width="154.124" x="380.076"><![CDATA[........................................................62]]></word></line><line height="11.42" id="70004" y="104.614"><word id="70013" width="35.75" x="121.595"><![CDATA[SHARED]]></word><word id="70014" width="23.62" x="160.925"><![CDATA[READ]]></word></line></para><para height="8.904" id="70004" poly="m 117.1989 111.145996 l 117.1989 120.05 l 533.13086 120.05 l 533.13086 111.145996 z" width="415.932" x="117.199" y="111.146"><line height="14.317" id="70005" y="123.037"><word id="70015" width="171.292" x="117.199"><![CDATA[Vocabulary/Multiple-Meaning]]></word><word id="70016" width="36.19" x="292.942"><![CDATA[Words]]></word><word id="70017" width="188.32" x="330.473"><![CDATA[............................................................................]]></word><word id="70018" width="12.972" x="521.228"><![CDATA[66]]></word></line></para><para height="9.364" id="70005" poly="m 117.1989 127.686005 l 117.1989 137.05 l 532.6939 137.05 l 532.6939 127.686005 z" width="415.495" x="117.199" y="127.686"><line height="14.318" id="70006" y="140.037"><word id="70019" width="20.78" x="117.199"><![CDATA[Ask]]></word><word id="70020" width="20.861" x="142.43"><![CDATA[and]]></word><word id="70021" width="42.021" x="167.741"><![CDATA[Answer]]></word><word id="70022" width="55.177" x="214.213"><![CDATA[Questions]]></word><word id="70023" width="263.245" x="270.955"><![CDATA[....................................................................................................68]]></word></line></para><para height="8.559" id="70006" poly="m 117.1989 145.491 l 117.1989 154.05 l 533.1309 154.05 l 533.1309 145.491 z" width="415.932" x="117.199" y="145.491"><line height="14.317" id="70007" y="157.037"><word id="70024" width="53.107" x="117.199"><![CDATA[Captions,]]></word><word id="70025" width="33.396" x="174.756"><![CDATA[Maps,]]></word><word id="70026" width="20.861" x="212.603"><![CDATA[and]]></word><word id="70027" width="48.461" x="237.914"><![CDATA[Sidebars]]></word><word id="70028" width="230.48" x="288.316"><![CDATA[.............................................................................................]]></word><word id="70029" width="12.972" x="521.228"><![CDATA[69]]></word></line></para><para height="8.571" id="70007" poly="m 117.1989 162.47949 l 117.1989 171.05 l 532.8891 171.05 l 532.8891 162.47949 z" width="415.69" x="117.199" y="162.479"><line height="14.317" id="70008" y="174.037"><word id="70030" width="27.623" x="117.199"><![CDATA[Main]]></word><word id="70031" width="24.587" x="149.272"><![CDATA[Idea]]></word><word id="70032" width="20.861" x="178.31"><![CDATA[and]]></word><word id="70033" width="19.826" x="203.621"><![CDATA[Key]]></word><word id="70034" width="38.352" x="227.898"><![CDATA[Details]]></word><word id="70035" width="265.72" x="268.48"><![CDATA[.....................................................................................................70]]></word></line></para><para height="9.919" id="70008" poly="m 121.5945 178.13103 l 121.5945 188.05 l 532.49817 188.05 l 532.49817 178.13103 z" width="410.904" x="121.595" y="178.131"><line height="16.068" id="70009" y="191.3"><word id="70036" width="53.534" x="170.202"><![CDATA[Respond]]></word><word id="70037" width="13.169" x="228.767"><![CDATA[to]]></word><word id="70038" width="52.039" x="246.967"><![CDATA[Reading]]></word><word id="70039" width="233.482" x="300.718"><![CDATA[........................................................................................72]]></word></line><line height="11.42" id="70010" y="189.461"><word id="70040" width="37.14" x="121.595"><![CDATA[WRITING]]></word></line></para><para height="8.571" id="70009" poly="m 117.1987 196.47949 l 117.1987 205.05 l 532.7741 205.05 l 532.7741 196.47949 z" width="415.575" x="117.199" y="196.479"><line height="14.317" id="70011" y="208.037"><word id="70041" width="51.313" x="117.199"><![CDATA[Research]]></word><word id="70042" width="20.861" x="172.962"><![CDATA[and]]></word><word id="70043" width="39.537" x="198.274"><![CDATA[Inquiry]]></word><word id="70044" width="295.48" x="238.72"><![CDATA[.................................................................................................................73]]></word></line></para><para height="9.776" id="70010" poly="m 121.5946 212.274 l 121.5946 222.05 l 532.95825 222.05 l 532.95825 212.274 z" width="411.364" x="121.595" y="212.274"><line height="16.068" id="70012" y="225.3"><word id="70045" width="51.025" x="195.203"><![CDATA[Analyze]]></word><word id="70046" width="63.362" x="251.259"><![CDATA[Protecting]]></word><word id="70047" width="22.581" x="319.158"><![CDATA[Our]]></word><word id="70048" width="32.071" x="346.276"><![CDATA[Parks]]></word><word id="70049" width="154.126" x="380.074"><![CDATA[........................................................74]]></word></line><line height="11.42" id="70013" y="223.614"><word id="70050" width="37.21" x="121.595"><![CDATA[ANCHOR]]></word><word id="70051" width="22.13" x="162.385"><![CDATA[TEXT]]></word></line></para><para height="9.919" id="70011" poly="m 121.5945 229.13103 l 121.5945 239.05 l 533.13074 239.05 l 533.13074 229.13103 z" width="411.536" x="121.595" y="229.131"><line height="16.068" id="70014" y="242.3"><word id="70052" width="53.534" x="170.202"><![CDATA[Respond]]></word><word id="70053" width="13.169" x="228.767"><![CDATA[to]]></word><word id="70054" width="52.039" x="246.967"><![CDATA[Reading]]></word><word id="70055" width="233.482" x="300.718"><![CDATA[........................................................................................76]]></word></line><line height="11.42" id="70015" y="240.461"><word id="70056" width="37.14" x="121.595"><![CDATA[WRITING]]></word></line></para><para height="11.174" id="70012" poly="m 121.5945 245.52 l 121.5945 256.6944 l 532.4866 256.6944 l 532.4866 245.52 z" width="410.892" x="121.595" y="245.52"><line height="16.068" id="70016" y="258.614"><word id="70057" width="31.06" x="121.595"><![CDATA[PAIRED]]></word><word id="70058" width="46.73" x="156.235"><![CDATA[SELECTION]]></word><word id="70059" width="51.025" x="212.205"><![CDATA[Analyze]]></word><word id="70060" width="14.391" x="268.261"><![CDATA[“5]]></word><word id="70061" width="62.374" x="287.683"><![CDATA[Questions]]></word><word id="70062" width="18.031" x="355.088"><![CDATA[for]]></word><word id="70063" width="46.839" x="378.15"><![CDATA[George]]></word><word id="70064" width="71.253" x="430.02"><![CDATA[McDonald”]]></word><word id="70065" width="32.605" x="501.595"><![CDATA[.......77]]></word></line></para><para height="8.559" id="70013" poly="m 117.1986 264.491 l 117.1986 273.05 l 533.13074 273.05 l 533.13074 264.491 z" width="415.932" x="117.199" y="264.491"><line height="14.317" id="70017" y="276.037"><word id="70066" width="48.334" x="117.199"><![CDATA[Author's]]></word><word id="70067" width="32.936" x="169.984"><![CDATA[Craft:]]></word><word id="70068" width="48.335" x="207.37"><![CDATA[Author’s]]></word><word id="70069" width="44.379" x="260.155"><![CDATA[Purpose]]></word><word id="70070" width="228.526" x="305.674"><![CDATA[......................................................................................79]]></word></line></para><para height="8.904" id="70014" poly="m 117.1987 281.146 l 117.1987 290.05 l 532.8892 290.05 l 532.8892 281.146 z" width="415.691" x="117.199" y="281.146"><line height="14.317" id="70018" y="293.037"><word id="70071" width="24.311" x="117.199"><![CDATA[Text]]></word><word id="70072" width="128.743" x="145.96"><![CDATA[Connections/Accuracy]]></word><word id="70073" width="20.861" x="279.153"><![CDATA[and]]></word><word id="70074" width="47.874" x="304.465"><![CDATA[Phrasing]]></word><word id="70075" width="181.409" x="352.791"><![CDATA[...................................................................80]]></word></line></para><para height="9.919" id="70015" poly="m 121.5945 297.131 l 121.5945 307.05 l 532.49817 307.05 l 532.49817 297.131 z" width="410.904" x="121.595" y="297.131"><line height="16.068" id="70019" y="310.3"><word id="70076" width="96.187" x="170.202"><![CDATA[Argumentative]]></word><word id="70077" width="27.482" x="271.42"><![CDATA[Text]]></word><word id="70078" width="233.481" x="300.719"><![CDATA[........................................................................................82]]></word></line><line height="11.42" id="70020" y="308.461"><word id="70079" width="37.14" x="121.595"><![CDATA[WRITING]]></word></line></para><para height="16.776" id="70016" poly="m 108.9353 348.356 l 108.9353 365.132 l 306.4313 365.132 l 306.4313 348.356 z" width="197.496" x="108.935" y="348.356"><line height="27.24" id="70021" y="369.74"><word id="70080" width="62.232" x="108.935"><![CDATA[WRAP]]></word><word id="70081" width="26.952" x="179.783"><![CDATA[UP]]></word><word id="70082" width="37.56" x="215.351"><![CDATA[THE]]></word><word id="70083" width="45.144" x="261.527"><![CDATA[UNIT]]></word></line></para><para height="7.18" id="70017" poly="m 121.5946 393.7713 l 121.5946 400.9513 l 241.94461 400.9513 l 241.94461 393.7713 z" width="120.35" x="121.595" y="393.771"><line height="11.42" id="70022" y="402.871"><word id="70084" width="5.95" x="121.595"><![CDATA[S]]></word><word id="70085" width="5.78" x="127.745"><![CDATA[H]]></word><word id="70086" width="6.41" x="133.725"><![CDATA[O]]></word><word id="70087" width="8.47" x="139.995"><![CDATA[W]]></word><word id="70088" width="8.47" x="152.045"><![CDATA[W]]></word><word id="70089" width="5.78" x="160.715"><![CDATA[H]]></word><word id="70090" width="6.16" x="166.695"><![CDATA[A]]></word><word id="70091" width="5.17" x="172.205"><![CDATA[T]]></word><word id="70092" width="6.06" x="180.955"><![CDATA[Y]]></word><word id="70093" width="6.41" x="186.815"><![CDATA[O]]></word><word id="70094" width="5.8" x="193.425"><![CDATA[U]]></word><word id="70095" width="4.86" x="202.805"><![CDATA[L]]></word><word id="70096" width="4.75" x="207.865"><![CDATA[E]]></word><word id="70097" width="6.16" x="212.815"><![CDATA[A]]></word><word id="70098" width="6.01" x="219.175"><![CDATA[R]]></word><word id="70099" width="5.92" x="225.385"><![CDATA[N]]></word><word id="70100" width="11.05" x="231.505"><![CDATA[ED]]></word></line></para><para height="8.901" id="70018" poly="m 140.6127 409.0895 l 140.6127 417.9905 l 532.2972 417.9905 l 532.2972 409.0895 z" width="391.684" x="140.613" y="409.089"><line height="14.318" id="70023" y="420.98"><word id="70101" width="4.025" x="140.613"><![CDATA[•]]></word><word id="70102" width="59.191" x="149.088"><![CDATA[Expository]]></word><word id="70103" width="27.876" x="212.729"><![CDATA[Text:]]></word><word id="70104" width="84.628" x="245.056"><![CDATA[“Remembering]]></word><word id="70105" width="19.803" x="334.135"><![CDATA[San]]></word><word id="70106" width="175.22" x="358.388"><![CDATA[Jacinto”.............................................90]]></word></line></para><para height="8.571" id="70019" poly="m 140.6072 426.4198 l 140.6072 434.9903 l 532.1822 434.9903 l 532.1822 426.4198 z" width="391.575" x="140.607" y="426.42"><line height="14.317" id="70024" y="437.977"><word id="70107" width="4.025" x="140.607"><![CDATA[•]]></word><word id="70108" width="48.277" x="149.083"><![CDATA[Realistic]]></word><word id="70109" width="41.975" x="201.81"><![CDATA[Fiction:]]></word><word id="70110" width="42.86" x="248.236"><![CDATA[“Sofia's]]></word><word id="70111" width="47.483" x="295.547"><![CDATA[Mexican]]></word><word id="70112" width="54.487" x="347.481"><![CDATA[Birthday”]]></word><word id="70113" width="113.92" x="404.283"><![CDATA[..............................................]]></word><word id="70114" width="12.891" x="520.717"><![CDATA[93]]></word></line></para><para height="7.18" id="70020" poly="m 121.5946 449.379 l 121.5946 456.559 l 230.18462 456.559 l 230.18462 449.379 z" width="108.59" x="121.595" y="449.379"><line height="11.42" id="70025" y="458.479"><word id="70115" width="4.75" x="121.595"><![CDATA[E]]></word></line><line height="11.42" id="70026" y="458.479"><word id="70116" width="6.44" x="126.545"><![CDATA[X]]></word></line><line height="11.42" id="70027" y="458.479"><word id="70117" width="5.17" x="133.185"><![CDATA[T]]></word></line><line height="11.42" id="70028" y="458.479"><word id="70118" width="4.75" x="138.555"><![CDATA[E]]></word></line><line height="11.42" id="70029" y="458.479"><word id="70119" width="5.92" x="143.505"><![CDATA[N]]></word></line><line height="11.42" id="70030" y="458.479"><word id="70120" width="6.1" x="149.625"><![CDATA[D]]></word></line><line height="11.42" id="70031" y="458.479"><word id="70121" width="6.06" x="159.305"><![CDATA[Y]]></word></line><line height="11.42" id="70032" y="458.479"><word id="70122" width="6.41" x="165.165"><![CDATA[O]]></word></line><line height="11.42" id="70033" y="458.479"><word id="70123" width="5.8" x="171.775"><![CDATA[U]]></word></line><line height="11.42" id="70034" y="458.479"><word id="70124" width="6.01" x="177.775"><![CDATA[R]]></word></line><line height="11.42" id="70035" y="458.479"><word id="70125" width="4.86" x="187.365"><![CDATA[L]]></word></line><line height="11.42" id="70036" y="458.479"><word id="70126" width="4.75" x="192.425"><![CDATA[E]]></word></line><line height="11.42" id="70037" y="458.479"><word id="70127" width="6.16" x="197.375"><![CDATA[A]]></word></line><line height="11.42" id="70038" y="458.479"><word id="70128" width="6.01" x="203.735"><![CDATA[R]]></word></line><line height="11.42" id="70039" y="458.479"><word id="70129" width="5.92" x="209.945"><![CDATA[N]]></word></line><line height="11.42" id="70040" y="458.479"><word id="70130" width="2.07" x="216.065"><![CDATA[I]]></word></line><line height="11.42" id="70041" y="458.479"><word id="70131" width="12.35" x="218.335"><![CDATA[NG]]></word></line></para><para height="8.905" id="70021" poly="m 140.6072 464.0853 l 140.6072 472.9903 l 532.53876 472.9903 l 532.53876 464.0853 z" width="391.932" x="140.607" y="464.085"><line height="14.317" id="70042" y="475.976"><word id="70132" width="4.025" x="140.607"><![CDATA[•]]></word><word id="70133" width="61.95" x="149.083"><![CDATA[Comparing]]></word><word id="70134" width="39.157" x="215.484"><![CDATA[Genres]]></word><word id="70135" width="262.72" x="255.486"><![CDATA[..........................................................................................................]]></word><word id="70136" width="12.972" x="520.636"><![CDATA[96]]></word></line></para><para height="8.904" id="70022" poly="m 140.6073 481.0863 l 140.6073 489.9903 l 531.8947 489.9903 l 531.8947 481.0863 z" width="391.287" x="140.607" y="481.086"><line height="14.317" id="70043" y="492.977"><word id="70137" width="4.025" x="140.607"><![CDATA[•]]></word><word id="70138" width="70.046" x="149.083"><![CDATA[Homographs]]></word><word id="70139" width="312.841" x="220.767"><![CDATA[........................................................................................................................97]]></word></line></para><para height="8.248" id="70023" poly="m 140.6072 498.7418 l 140.6072 506.9903 l 532.5388 506.9903 l 532.5388 498.7418 z" width="391.932" x="140.607" y="498.742"><line height="14.317" id="70044" y="509.977"><word id="70140" width="4.025" x="140.607"><![CDATA[•]]></word><word id="70141" width="47.288" x="149.083"><![CDATA[Connect]]></word><word id="70142" width="11.65" x="200.821"><![CDATA[to]]></word><word id="70143" width="45.552" x="216.921"><![CDATA[Content]]></word><word id="70144" width="255.28" x="262.925"><![CDATA[.......................................................................................................]]></word><word id="70145" width="12.972" x="520.636"><![CDATA[99]]></word></line></para><para height="7.18" id="70024" poly="m 121.5946 521.4881 l 121.5946 528.6681 l 231.01459 528.6681 l 231.01459 521.4881 z" width="109.42" x="121.595" y="521.488"><line height="11.42" id="70045" y="530.588"><word id="70146" width="5.17" x="121.595"><![CDATA[T]]></word></line><line height="11.42" id="70046" y="530.588"><word id="70147" width="6.01" x="126.965"><![CDATA[R]]></word></line><line height="11.42" id="70047" y="530.588"><word id="70148" width="6.16" x="133.175"><![CDATA[A]]></word></line><line height="11.42" id="70048" y="530.588"><word id="70149" width="5.93" x="139.535"><![CDATA[C]]></word></line><line height="11.42" id="70049" y="530.588"><word id="70150" width="5.83" x="145.665"><![CDATA[K]]></word></line><line height="11.42" id="70050" y="530.588"><word id="70151" width="6.06" x="155.075"><![CDATA[Y]]></word></line><line height="11.42" id="70051" y="530.588"><word id="70152" width="6.41" x="160.935"><![CDATA[O]]></word></line><line height="11.42" id="70052" y="530.588"><word id="70153" width="5.8" x="167.545"><![CDATA[U]]></word></line><line height="11.42" id="70053" y="530.588"><word id="70154" width="6.01" x="173.545"><![CDATA[R]]></word></line><line height="11.42" id="70054" y="530.588"><word id="70155" width="5.6" x="183.135"><![CDATA[P]]></word></line><line height="11.42" id="70055" y="530.588"><word id="70156" width="6.01" x="188.935"><![CDATA[R]]></word></line><line height="11.42" id="70056" y="530.588"><word id="70157" width="6.41" x="195.145"><![CDATA[O]]></word></line><line height="11.42" id="70057" y="530.588"><word id="70158" width="6.23" x="201.755"><![CDATA[G]]></word></line><line height="11.42" id="70058" y="530.588"><word id="70159" width="6.01" x="208.185"><![CDATA[R]]></word></line><line height="11.42" id="70059" y="530.588"><word id="70160" width="4.75" x="214.395"><![CDATA[E]]></word></line><line height="11.42" id="70060" y="530.588"><word id="70161" width="12.1" x="219.345"><![CDATA[SS]]></word></line></para><para height="8.261" id="70025" poly="m 140.6073 536.7293 l 140.6073 544.9903 l 532.2972 544.9903 l 532.2972 536.7293 z" width="391.69" x="140.607" y="536.729"><line height="14.317" id="70061" y="547.976"><word id="70162" width="4.025" x="140.607"><![CDATA[•]]></word><word id="70163" width="31.567" x="149.083"><![CDATA[What]]></word><word id="70164" width="17.882" x="185.101"><![CDATA[Did]]></word><word id="70165" width="20.504" x="207.434"><![CDATA[You]]></word><word id="70166" width="37.95" x="232.389"><![CDATA[Learn?]]></word><word id="70167" width="260.761" x="272.847"><![CDATA[.................................................................................................100]]></word></line></para><para height="8.568" id="70026" poly="m 116.6067 557.4218 l 116.6067 565.9903 l 532.1593 565.9903 l 532.1593 557.4218 z" width="415.553" x="116.607" y="557.422"><line height="14.318" id="70062" y="568.979"><word id="70168" width="51.313" x="116.607"><![CDATA[Research]]></word><word id="70169" width="20.861" x="172.37"><![CDATA[and]]></word><word id="70170" width="39.537" x="197.682"><![CDATA[Inquiry]]></word><word id="70171" width="295.48" x="238.128"><![CDATA[................................................................................................................101]]></word></line></para><para height="11.497" id="70027" poly="m 130.0476 598.855 l 130.0476 610.3519 l 488.1076 610.3519 l 488.1076 598.855 z" width="358.06" x="130.048" y="598.855"><line height="16.856" id="70063" y="613.667"><word id="70172" width="35.994" x="130.048"><![CDATA[Digital]]></word><word id="70173" width="31.248" x="169.99"><![CDATA[Tools]]></word></line><line height="12.45" id="70064" y="612.752"><word id="70174" width="19.29" x="207.538"><![CDATA[Find]]></word><word id="70175" width="16.22" x="229.918"><![CDATA[this]]></word><word id="70176" width="28.35" x="249.228"><![CDATA[eBook]]></word><word id="70177" width="17.51" x="280.668"><![CDATA[and]]></word><word id="70178" width="24.76" x="301.268"><![CDATA[other]]></word><word id="70179" width="43.03" x="329.118"><![CDATA[resources]]></word><word id="70180" width="9.73" x="375.238"><![CDATA[at]]></word><word id="70181" width="101.08" x="388.058"><![CDATA[my.mheducation.com]]></word></line></para><para height="5.808" id="70028" poly="m 728.2845 624.1925 l 728.2845 630.0 l 733.264 630.0 l 733.264 624.1925 z" width="4.979" x="728.285" y="624.192"><line height="13.397" id="70065" y="632.737"><word id="70182" width="5.715" x="728.285"><![CDATA[v]]></word></line></para><para height="168.209" id="70029" poly="m 38.47 442.1428 l 38.47 610.3518 l 39.241 610.3518 l 39.241 442.1428 z" width="0.771" x="38.47" y="442.143"><line height="36.528" id="70066" y="611.792"><word id="70183" width="2.148" x="38.47"><![CDATA[(]]></word><word id="70184" width="2.256" x="38.47"><![CDATA[t]]></word><word id="70185" width="2.148" x="38.47"><![CDATA[)]]></word><word id="70186" width="2.982" x="38.47"><![CDATA[J]]></word><word id="70187" width="3.504" x="38.47"><![CDATA[o]]></word><word id="70188" width="2.322" x="38.47"><![CDATA[r]]></word><word id="70189" width="3.594" x="38.47"><![CDATA[g]]></word><word id="70190" width="4.182" x="38.47"><![CDATA[H]]></word><word id="70191" width="3.582" x="38.47"><![CDATA[a]]></word><word id="70192" width="3.09" x="38.47"><![CDATA[c]]></word><word id="70193" width="3.24" x="38.47"><![CDATA[k]]></word><word id="70194" width="3.378" x="38.47"><![CDATA[e]]></word><word id="70195" width="5.262" x="38.47"><![CDATA[m]]></word><word id="70196" width="3.582" x="38.47"><![CDATA[a]]></word><word id="70197" width="3.396" x="38.47"><![CDATA[n]]></word><word id="70198" width="3.396" x="38.47"><![CDATA[n]]></word><word id="70199" width="2.934" x="38.47"><![CDATA[/]]></word><word id="70200" width="3.276" x="38.47"><![CDATA[S]]></word><word id="70201" width="3.396" x="38.47"><![CDATA[h]]></word><word id="70202" width="3.396" x="38.47"><![CDATA[u]]></word><word id="70203" width="2.256" x="38.47"><![CDATA[t]]></word><word id="70204" width="2.256" x="38.47"><![CDATA[t]]></word><word id="70205" width="3.378" x="38.47"><![CDATA[e]]></word><word id="70206" width="2.322" x="38.47"><![CDATA[r]]></word><word id="70207" width="2.454" x="38.47"><![CDATA[s]]></word><word id="70208" width="2.256" x="38.47"><![CDATA[t]]></word><word id="70209" width="3.504" x="38.47"><![CDATA[o]]></word><word id="70210" width="3.09" x="38.47"><![CDATA[c]]></word><word id="70211" width="3.24" x="38.47"><![CDATA[k]]></word><word id="70212" width="1.74" x="38.47"><![CDATA[;]]></word><word id="70213" width="2.148" x="38.47"><![CDATA[(]]></word><word id="70214" width="3.534" x="38.47"><![CDATA[b]]></word><word id="70215" width="2.148" x="38.47"><![CDATA[)]]></word><word id="70216" width="5.634" x="38.47"><![CDATA[M]]></word><word id="70217" width="1.626" x="38.47"><![CDATA[i]]></word><word id="70218" width="3.582" x="38.47"><![CDATA[a]]></word><word id="70219" width="5.262" x="38.47"><![CDATA[m]]></word><word id="70220" width="1.626" x="38.47"><![CDATA[i]]></word><word id="70221" width="3.588" x="38.47"><![CDATA[2]]></word><word id="70222" width="2.982" x="38.47"><![CDATA[y]]></word><word id="70223" width="3.504" x="38.47"><![CDATA[o]]></word><word id="70224" width="3.396" x="38.47"><![CDATA[u]]></word><word id="70225" width="2.934" x="38.47"><![CDATA[/]]></word><word id="70226" width="3.276" x="38.47"><![CDATA[S]]></word><word id="70227" width="3.396" x="38.47"><![CDATA[h]]></word><word id="70228" width="3.396" x="38.47"><![CDATA[u]]></word><word id="70229" width="2.256" x="38.47"><![CDATA[t]]></word><word id="70230" width="2.256" x="38.47"><![CDATA[t]]></word><word id="70231" width="3.378" x="38.47"><![CDATA[e]]></word><word id="70232" width="2.322" x="38.47"><![CDATA[r]]></word><word id="70233" width="2.454" x="38.47"><![CDATA[s]]></word><word id="70234" width="2.256" x="38.47"><![CDATA[t]]></word><word id="70235" width="3.504" x="38.47"><![CDATA[o]]></word><word id="70236" width="3.09" x="38.47"><![CDATA[c]]></word><word id="70237" width="3.24" x="38.47"><![CDATA[k]]></word></line></para></page></pages>