<?xml version="1.0" encoding="UTF-8"?>
<pages><page><para height="23.461" id="580001" poly="m 104.4 90.3757 l 104.4 113.8367 l 348.116 113.8367 l 348.116 90.3757 z" width="243.716" x="104.4" y="90.376"><line height="34.916" id="580001" y="121.928"><word id="580001" width="107.967" x="104.4"><![CDATA[Respond]]></word><word id="580002" width="24.882" x="219.965"><![CDATA[to]]></word><word id="580003" width="96.773" x="252.445"><![CDATA[Reading]]></word></line></para><para height="28.585" id="580002" poly="m 104.4 133.24896 l 104.4 161.83446 l 498.82578 161.83446 l 498.82578 133.24896 z" width="394.426" x="104.4" y="133.249"><line height="16.63" id="580002" y="147.257"><word id="580004" width="26.448" x="104.4"><![CDATA[Talk]]></word><word id="580005" width="38.076" x="134.966"><![CDATA[about]]></word><word id="580006" width="21.162" x="177.16"><![CDATA[the]]></word><word id="580007" width="47.139" x="202.44"><![CDATA[prompt]]></word><word id="580008" width="40.214" x="253.697"><![CDATA[below.]]></word><word id="580009" width="35.269" x="298.029"><![CDATA[Think]]></word><word id="580010" width="38.076" x="337.416"><![CDATA[about]]></word><word id="580011" width="21.162" x="379.61"><![CDATA[the]]></word><word id="580012" width="66.718" x="404.89"><![CDATA[characters]]></word><word id="580013" width="24.667" x="475.726"><![CDATA[and]]></word></line><line height="16.63" id="580003" y="165.254"><word id="580014" width="25.052" x="104.4"><![CDATA[plot]]></word><word id="580015" width="11.784" x="133.57"><![CDATA[in]]></word><word id="580016" width="21.161" x="149.473"><![CDATA[the]]></word><word id="580017" width="32.732" x="174.752"><![CDATA[story.]]></word><word id="580018" width="23.184" x="211.603"><![CDATA[Use]]></word><word id="580019" width="27.873" x="238.906"><![CDATA[your]]></word><word id="580020" width="34.585" x="270.897"><![CDATA[notes]]></word><word id="580021" width="24.667" x="309.6"><![CDATA[and]]></word><word id="580022" width="48.906" x="338.385"><![CDATA[graphic]]></word><word id="580023" width="63.185" x="391.409"><![CDATA[organizer.]]></word></line></para><para height="12.152" id="580003" poly="m 556.4 94.48992 l 556.4 106.6419 l 608.29803 106.6419 l 608.29803 94.48992 z" width="51.898" x="556.4" y="94.49"><line height="16.856" id="580004" y="110.548"><word id="580024" width="32.256" x="556.4"><![CDATA[Quick]]></word><word id="580025" width="16.576" x="592.324"><![CDATA[Tip]]></word></line></para><para height="40.817" id="580004" poly="m 556.2 125.506256 l 556.2 166.3232 l 672.56274 166.3232 l 672.56274 125.506256 z" width="116.363" x="556.2" y="125.506"><line height="14.296" id="580005" y="137.266"><word id="580026" width="19.931" x="556.2"><![CDATA[Use]]></word><word id="580027" width="29.853" x="580.051"><![CDATA[these]]></word><word id="580028" width="49.245" x="613.824"><![CDATA[sentence]]></word></line><line height="14.296" id="580006" y="153.265"><word id="580029" width="40.829" x="556.2"><![CDATA[starters]]></word><word id="580030" width="11.148" x="600.949"><![CDATA[to]]></word><word id="580031" width="20.996" x="616.017"><![CDATA[talk]]></word><word id="580032" width="32.732" x="640.933"><![CDATA[about]]></word></line><line height="14.296" id="580007" y="169.263"><word id="580033" width="23.153" x="556.2"><![CDATA[how]]></word><word id="580034" width="28.372" x="583.272"><![CDATA[Peter]]></word><word id="580035" width="28.015" x="615.564"><![CDATA[feels.]]></word></line></para><para height="97.449" id="580005" poly="m 556.2 176.88269 l 556.2 274.33145 l 687.2383 274.33145 l 687.2383 176.88269 z" width="131.038" x="556.2" y="176.883"><line height="14.296" id="580008" y="189.267"><word id="580036" width="12.887" x="556.2"><![CDATA[At]]></word><word id="580037" width="18.191" x="573.007"><![CDATA[the]]></word><word id="580038" width="55.248" x="595.118"><![CDATA[beginning]]></word><word id="580039" width="3.638" x="654.286"><![CDATA[I]]></word><word id="580040" width="25.296" x="661.844"><![CDATA[read]]></word></line><line height="14.296" id="580009" y="205.266"><word id="580041" width="23.091" x="556.2"><![CDATA[that]]></word><word id="580042" width="28.371" x="583.211"><![CDATA[Peter]]></word><word id="580043" width="2.61" x="612.868"><![CDATA[.]]></word><word id="580044" width="2.609" x="616.764"><![CDATA[.]]></word><word id="580045" width="2.609" x="620.66"><![CDATA[.]]></word></line><line height="14.296" id="580010" y="225.27"><word id="580046" width="20.592" x="556.2"><![CDATA[The]]></word><word id="580047" width="37.069" x="580.712"><![CDATA[author]]></word><word id="580048" width="28.983" x="621.701"><![CDATA[helps]]></word><word id="580049" width="17.518" x="654.604"><![CDATA[me]]></word></line><line height="14.296" id="580011" y="241.269"><word id="580050" width="61.813" x="556.2"><![CDATA[understand]]></word><word id="580051" width="12.862" x="621.934"><![CDATA[by]]></word><word id="580052" width="2.61" x="636.082"><![CDATA[.]]></word><word id="580053" width="2.609" x="639.978"><![CDATA[.]]></word><word id="580054" width="2.61" x="643.873"><![CDATA[.]]></word></line><line height="14.296" id="580012" y="261.273"><word id="580055" width="12.887" x="556.2"><![CDATA[At]]></word><word id="580056" width="18.191" x="573.007"><![CDATA[the]]></word><word id="580057" width="20.788" x="595.118"><![CDATA[end]]></word><word id="580058" width="11.172" x="619.827"><![CDATA[of]]></word><word id="580059" width="18.191" x="634.919"><![CDATA[the]]></word><word id="580060" width="30.049" x="657.03"><![CDATA[story,]]></word></line><line height="14.296" id="580013" y="277.271"><word id="580061" width="28.371" x="556.2"><![CDATA[Peter]]></word><word id="580062" width="2.61" x="585.857"><![CDATA[.]]></word><word id="580063" width="2.609" x="589.753"><![CDATA[.]]></word><word id="580064" width="2.61" x="593.648"><![CDATA[.]]></word></line></para><para height="10.99" id="580006" poly="m 554.3621 315.6512 l 554.3621 326.6412 l 689.3921 326.6412 l 689.3921 315.6512 z" width="135.03" x="554.362" y="315.651"><line height="16.856" id="580014" y="330.547"><word id="580065" width="55.594" x="554.362"><![CDATA[Grammar]]></word><word id="580066" width="76.16" x="613.624"><![CDATA[Connections]]></word></line></para><para height="105.093" id="580007" poly="m 556.163 346.58887 l 556.163 451.6816 l 682.387 451.6816 l 682.387 346.58887 z" width="126.224" x="556.163" y="346.589"><line height="14.296" id="580015" y="358.631"><word id="580067" width="27.955" x="556.163"><![CDATA[After]]></word><word id="580068" width="19.6" x="588.038"><![CDATA[you]]></word><word id="580069" width="28.199" x="611.558"><![CDATA[write]]></word><word id="580070" width="24.255" x="643.677"><![CDATA[your]]></word></line><line height="14.296" id="580016" y="374.629"><word id="580071" width="52.161" x="556.163"><![CDATA[response,]]></word><word id="580072" width="25.32" x="612.244"><![CDATA[read]]></word><word id="580073" width="7.644" x="641.484"><![CDATA[it]]></word><word id="580074" width="24.01" x="653.048"><![CDATA[over]]></word></line><line height="14.296" id="580017" y="390.628"><word id="580075" width="11.344" x="556.163"><![CDATA[to]]></word><word id="580076" width="30.552" x="571.426"><![CDATA[make]]></word><word id="580077" width="23.042" x="605.898"><![CDATA[sure]]></word><word id="580078" width="22.601" x="632.86"><![CDATA[that]]></word><word id="580079" width="19.6" x="659.382"><![CDATA[you]]></word></line><line height="14.296" id="580018" y="406.626"><word id="580080" width="18.375" x="556.163"><![CDATA[are]]></word><word id="580081" width="28.886" x="578.458"><![CDATA[using]]></word><word id="580082" width="51.854" x="611.264"><![CDATA[complete]]></word></line><line height="14.296" id="580019" y="422.625"><word id="580083" width="56.62" x="556.163"><![CDATA[sentences.]]></word><word id="580084" width="38.881" x="616.703"><![CDATA[Reread]]></word><word id="580085" width="24.255" x="659.504"><![CDATA[your]]></word></line><line height="14.296" id="580020" y="438.623"><word id="580086" width="48.779" x="556.163"><![CDATA[response]]></word><word id="580087" width="11.343" x="608.863"><![CDATA[to]]></word><word id="580088" width="30.552" x="624.126"><![CDATA[make]]></word><word id="580089" width="23.042" x="658.598"><![CDATA[sure]]></word></line><line height="14.296" id="580021" y="454.622"><word id="580090" width="7.644" x="556.163"><![CDATA[it]]></word><word id="580091" width="35.366" x="567.727"><![CDATA[makes]]></word><word id="580092" width="32.56" x="607.013"><![CDATA[sense.]]></word></line></para><para height="16.63" id="580008" poly="m 102.585 190.681 l 102.585 207.311 l 509.28 207.311 l 509.28 190.681 z" width="406.695" x="102.585" y="190.681"><line height="16.63" id="580022" y="207.311"><word id="580093" width="29.369" x="102.585"><![CDATA[How]]></word><word id="580094" width="30.281" x="136.215"><![CDATA[does]]></word><word id="580095" width="21.104" x="170.757"><![CDATA[the]]></word><word id="580096" width="42.978" x="196.122"><![CDATA[author]]></word><word id="580097" width="28.058" x="243.361"><![CDATA[help]]></word><word id="580098" width="22.928" x="275.68"><![CDATA[you]]></word><word id="580099" width="73.444" x="302.869"><![CDATA[understand]]></word><word id="580100" width="27.545" x="380.574"><![CDATA[how]]></word><word id="580101" width="42.878" x="412.38"><![CDATA[Peter’s]]></word><word id="580102" width="49.761" x="459.519"><![CDATA[feelings]]></word></line></para><para height="16.63" id="580009" poly="m 102.585 208.679 l 102.585 225.309 l 437.061 225.309 l 437.061 208.679 z" width="334.476" x="102.585" y="208.679"><line height="16.63" id="580023" y="225.309"><word id="580103" width="47.951" x="102.585"><![CDATA[change]]></word><word id="580104" width="30.609" x="154.797"><![CDATA[from]]></word><word id="580105" width="21.104" x="189.667"><![CDATA[the]]></word><word id="580106" width="64.495" x="215.032"><![CDATA[beginning]]></word><word id="580107" width="13.139" x="283.788"><![CDATA[of]]></word><word id="580108" width="21.105" x="301.187"><![CDATA[the]]></word><word id="580109" width="31.906" x="326.552"><![CDATA[story]]></word><word id="580110" width="13.252" x="362.719"><![CDATA[to]]></word><word id="580111" width="21.104" x="380.232"><![CDATA[the]]></word><word id="580112" width="31.464" x="405.597"><![CDATA[end?]]></word></line></para><para height="314.693" id="580010" poly="m 98.6618 232.063 l 98.6618 546.756 l 513.443 546.756 l 513.443 232.063 z" width="414.781" x="98.662" y="232.063"/><para height="8.199" id="580011" poly="m 22.0 621.8005 l 22.0 630.0 l 34.684498 630.0 l 34.684498 621.8005 z" width="12.684" x="22.0" y="621.801"><line height="13.42" id="580024" y="632.76"><word id="580113" width="14.191" x="22"><![CDATA[48]]></word></line><line height="9.336" id="580025" y="631.92"><word id="580114" width="15.584" x="57.5"><![CDATA[Unit]]></word><word id="580115" width="2.936" x="75.876"><![CDATA[1]]></word><word id="580116" width="2.8" x="81.604"><![CDATA[•]]></word><word id="580117" width="32.12" x="87.196"><![CDATA[Realistic]]></word><word id="580118" width="25.656" x="122.108"><![CDATA[Fiction]]></word></line></para><para height="24.391" id="580012" poly="m 41.8651 37.738625 l 41.8651 62.1294 l 309.78897 62.1294 l 309.78897 37.738625 z" width="267.924" x="41.865" y="37.739"><line height="32.547" id="580026" y="63.36"><word id="580119" width="101.887" x="132.12"><![CDATA[SHARED]]></word><word id="580120" width="67.317" x="244.211"><![CDATA[READ]]></word></line><line height="29.08" id="580027" y="67.329"><word id="580121" width="67.227" x="41.865"><![CDATA[Reread]]></word></line></para><para height="4.66" id="580013" poly="m 47.8692 156.23871 l 47.8692 160.8992 l 94.2207 160.8992 l 94.2207 156.23871 z" width="46.352" x="47.869" y="156.239"><line height="8.047" id="580028" y="162.544"><word id="580122" width="47.151" x="47.869"><![CDATA[COLLABORATE]]></word></line></para><para height="5.76" id="580014" poly="m 558.26 624.24 l 558.26 630.0 l 690.804 630.0 l 690.804 624.24 z" width="132.544" x="558.26" y="624.24"><line height="9.888" id="580029" y="632"><word id="580123" width="19.176" x="558.26"><![CDATA[TEKS]]></word><word id="580124" width="23.672" x="579.908"><![CDATA[3.7(B),]]></word><word id="580125" width="24.296" x="606.052"><![CDATA[3.7(C),]]></word><word id="580126" width="24.368" x="632.82"><![CDATA[3.8(C),]]></word><word id="580127" width="31.144" x="659.66"><![CDATA[3.11(D)(i)]]></word></line></para></page></pages>