<?xml version="1.0" encoding="UTF-8"?>
<pages><page><para height="23.461" id="1600001" poly="m 104.4 88.4757 l 104.4 111.9367 l 348.116 111.9367 l 348.116 88.4757 z" width="243.716" x="104.4" y="88.476"><line height="34.916" id="1600001" y="120.028"><word id="1600001" width="107.967" x="104.4"><![CDATA[Respond]]></word><word id="1600002" width="24.882" x="219.965"><![CDATA[to]]></word><word id="1600003" width="96.773" x="252.445"><![CDATA[Reading]]></word></line></para><para height="28.585" id="1600002" poly="m 104.4 131.34897 l 104.4 159.93445 l 487.31177 159.93445 l 487.31177 131.34897 z" width="382.912" x="104.4" y="131.349"><line height="16.63" id="1600002" y="145.357"><word id="1600004" width="26.448" x="104.4"><![CDATA[Talk]]></word><word id="1600005" width="38.076" x="134.966"><![CDATA[about]]></word><word id="1600006" width="21.162" x="177.16"><![CDATA[the]]></word><word id="1600007" width="47.139" x="202.44"><![CDATA[prompt]]></word><word id="1600008" width="40.214" x="253.697"><![CDATA[below.]]></word><word id="1600009" width="35.269" x="298.029"><![CDATA[Think]]></word><word id="1600010" width="38.076" x="337.416"><![CDATA[about]]></word><word id="1600011" width="21.162" x="379.61"><![CDATA[the]]></word><word id="1600012" width="41.396" x="404.89"><![CDATA[theme]]></word><word id="1600013" width="12.996" x="450.404"><![CDATA[of]]></word><word id="1600014" width="21.161" x="467.519"><![CDATA[the]]></word></line><line height="16.63" id="1600003" y="163.354"><word id="1600015" width="32.732" x="104.4"><![CDATA[story.]]></word><word id="1600016" width="23.185" x="141.25"><![CDATA[Use]]></word><word id="1600017" width="27.873" x="168.553"><![CDATA[your]]></word><word id="1600018" width="34.585" x="200.545"><![CDATA[notes]]></word><word id="1600019" width="24.667" x="239.248"><![CDATA[and]]></word><word id="1600020" width="48.906" x="268.033"><![CDATA[graphic]]></word><word id="1600021" width="63.185" x="321.057"><![CDATA[organizer.]]></word></line></para><para height="12.152" id="1600003" poly="m 551.5 93.318924 l 551.5 105.4709 l 603.39795 105.4709 l 603.39795 93.318924 z" width="51.898" x="551.5" y="93.319"><line height="16.856" id="1600004" y="109.377"><word id="1600022" width="32.256" x="551.5"><![CDATA[Quick]]></word><word id="1600023" width="16.576" x="587.424"><![CDATA[Tip]]></word></line></para><para height="40.817" id="1600004" poly="m 551.5 123.606094 l 551.5 164.4231 l 668.9285 164.4231 l 668.9285 123.606094 z" width="117.429" x="551.5" y="123.606"><line height="14.296" id="1600005" y="135.366"><word id="1600024" width="19.821" x="551.5"><![CDATA[Use]]></word><word id="1600025" width="29.572" x="575.24"><![CDATA[these]]></word><word id="1600026" width="49.221" x="608.732"><![CDATA[sentence]]></word></line><line height="14.296" id="1600006" y="151.365"><word id="1600027" width="41.724" x="551.5"><![CDATA[starters]]></word><word id="1600028" width="11.343" x="597.144"><![CDATA[to]]></word><word id="1600029" width="21.07" x="612.407"><![CDATA[talk]]></word><word id="1600030" width="32.634" x="637.397"><![CDATA[about]]></word></line><line height="14.296" id="1600007" y="167.363"><word id="1600031" width="69.935" x="551.5"><![CDATA[immigration.]]></word></line></para><para height="14.296" id="1600005" poly="m 653.69 209.074 l 653.69 223.37 l 661.947 223.37 l 661.947 209.074 z" width="8.257" x="653.69" y="209.074"><line height="14.296" id="1600008" y="223.37"><word id="1600032" width="8.257" x="653.69"><![CDATA[…]]></word></line></para><para height="80.825" id="1600006" poly="m 551.5 175.60738 l 551.5 256.43286 l 651.0689 256.43286 l 651.0689 175.60738 z" width="99.569" x="551.5" y="175.607"><line height="14.296" id="1600009" y="187.367"><word id="1600033" width="20.102" x="551.5"><![CDATA[The]]></word><word id="1600034" width="36.628" x="575.522"><![CDATA[author]]></word><word id="1600035" width="23.373" x="616.07"><![CDATA[uses]]></word></line><line height="14.296" id="1600010" y="203.366"><word id="1600036" width="48.363" x="551.5"><![CDATA[dialogue]]></word><word id="1600037" width="11.356" x="603.783"><![CDATA[to]]></word><word id="1600038" width="8.256" x="619.059"><![CDATA[…]]></word></line><line height="14.296" id="1600011" y="223.37"><word id="1600039" width="3.638" x="551.5"><![CDATA[I]]></word><word id="1600040" width="25.212" x="559.058"><![CDATA[read]]></word><word id="1600041" width="22.503" x="588.19"><![CDATA[that]]></word><word id="1600042" width="35.157" x="614.613"><![CDATA[Danny]]></word></line><line height="14.296" id="1600012" y="243.374"><word id="1600043" width="21.277" x="551.501"><![CDATA[This]]></word><word id="1600044" width="28.849" x="576.698"><![CDATA[helps]]></word><word id="1600045" width="17.518" x="609.467"><![CDATA[me]]></word></line><line height="14.296" id="1600013" y="259.373"><word id="1600046" width="62.255" x="551.5"><![CDATA[understand]]></word><word id="1600047" width="22.504" x="617.674"><![CDATA[that]]></word><word id="1600048" width="8.256" x="644.098"><![CDATA[…]]></word></line></para><para height="10.99" id="1600007" poly="m 551.462 299.22827 l 551.462 310.2183 l 686.492 310.2183 l 686.492 299.22827 z" width="135.03" x="551.462" y="299.228"><line height="16.856" id="1600014" y="314.124"><word id="1600049" width="55.594" x="551.462"><![CDATA[Grammar]]></word><word id="1600050" width="76.16" x="610.724"><![CDATA[Connections]]></word></line></para><para height="137.09" id="1600008" poly="m 551.46326 329.4551 l 551.46326 466.54486 l 672.7505 466.54486 l 672.7505 329.4551 z" width="121.287" x="551.463" y="329.455"><line height="14.296" id="1600015" y="341.497"><word id="1600051" width="13.426" x="551.463"><![CDATA[As]]></word><word id="1600052" width="19.6" x="568.809"><![CDATA[you]]></word><word id="1600053" width="28.2" x="592.329"><![CDATA[write]]></word><word id="1600054" width="24.255" x="624.449"><![CDATA[your]]></word></line><line height="14.296" id="1600016" y="357.495"><word id="1600055" width="52.149" x="551.463"><![CDATA[response,]]></word><word id="1600056" width="14.001" x="607.532"><![CDATA[be]]></word><word id="1600057" width="23.043" x="625.453"><![CDATA[sure]]></word><word id="1600058" width="11.343" x="652.416"><![CDATA[to]]></word></line><line height="14.296" id="1600017" y="373.494"><word id="1600059" width="32.585" x="551.463"><![CDATA[check]]></word><word id="1600060" width="22.602" x="587.968"><![CDATA[that]]></word><word id="1600061" width="19.599" x="614.49"><![CDATA[you]]></word><word id="1600062" width="26.116" x="638.01"><![CDATA[have]]></word></line><line height="14.296" id="1600018" y="389.492"><word id="1600063" width="60.417" x="551.463"><![CDATA[capitalized]]></word><word id="1600064" width="18.032" x="615.8"><![CDATA[the]]></word><word id="1600065" width="36.199" x="637.752"><![CDATA[names]]></word></line><line height="14.296" id="1600019" y="405.491"><word id="1600066" width="11.246" x="551.463"><![CDATA[of]]></word><word id="1600067" width="38.183" x="566.629"><![CDATA[people]]></word><word id="1600068" width="21.07" x="608.732"><![CDATA[and]]></word><word id="1600069" width="37.669" x="633.722"><![CDATA[places.]]></word></line><line height="14.296" id="1600020" y="421.489"><word id="1600070" width="60.332" x="551.463"><![CDATA[Remember]]></word><word id="1600071" width="11.344" x="615.714"><![CDATA[to]]></word><word id="1600072" width="18.547" x="630.978"><![CDATA[use]]></word><word id="1600073" width="7.314" x="653.444"><![CDATA[a]]></word></line><line height="14.296" id="1600021" y="437.488"><word id="1600074" width="66.616" x="551.463"><![CDATA[punctuation]]></word><word id="1600075" width="28.812" x="621.999"><![CDATA[mark]]></word></line><line height="14.296" id="1600022" y="453.486"><word id="1600076" width="11.479" x="551.463"><![CDATA[at]]></word><word id="1600077" width="18.032" x="566.862"><![CDATA[the]]></word><word id="1600078" width="20.825" x="588.814"><![CDATA[end]]></word><word id="1600079" width="11.246" x="613.558"><![CDATA[of]]></word><word id="1600080" width="26.803" x="628.724"><![CDATA[each]]></word></line><line height="14.296" id="1600023" y="469.485"><word id="1600081" width="51.659" x="551.463"><![CDATA[sentence.]]></word></line></para><para height="28.586" id="1600009" poly="m 102.5102 191.32843 l 102.5102 219.91396 l 492.88892 219.91396 l 492.88892 191.32843 z" width="390.379" x="102.51" y="191.328"><line height="16.63" id="1600024" y="205.336"><word id="1600082" width="28.799" x="102.51"><![CDATA[How]]></word><word id="1600083" width="29.269" x="135.428"><![CDATA[does]]></word><word id="1600084" width="21.162" x="168.815"><![CDATA[the]]></word><word id="1600085" width="43.12" x="194.095"><![CDATA[author]]></word><word id="1600086" width="28.029" x="241.334"><![CDATA[help]]></word><word id="1600087" width="22.5" x="273.482"><![CDATA[you]]></word><word id="1600088" width="71.905" x="300.101"><![CDATA[understand]]></word><word id="1600089" width="32.989" x="376.124"><![CDATA[what]]></word><word id="1600090" width="9.078" x="413.231"><![CDATA[it]]></word><word id="1600091" width="24.652" x="426.427"><![CDATA[was]]></word><word id="1600092" width="22.016" x="455.198"><![CDATA[like]]></word><word id="1600093" width="12.968" x="481.332"><![CDATA[to]]></word></line><line height="16.63" id="1600025" y="223.334"><word id="1600094" width="65.935" x="102.51"><![CDATA[immigrate]]></word><word id="1600095" width="12.968" x="172.563"><![CDATA[to]]></word><word id="1600096" width="61.332" x="189.649"><![CDATA[America?]]></word></line></para><para height="358.848" id="1600010" poly="m 102.96 222.72 l 102.96 581.5683 l 512.28 581.5683 l 512.28 222.72 z" width="409.32" x="102.96" y="222.72"/><para height="8.234" id="1600011" poly="m 22.0 621.766 l 22.0 630.0 l 39.1235 630.0 l 39.1235 621.766 z" width="17.124" x="22.0" y="621.766"><line height="13.42" id="1600026" y="632.76"><word id="1600097" width="18.434" x="22"><![CDATA[150]]></word><word id="1600098" width="15.584" x="57.5"><![CDATA[Unit]]></word><word id="1600099" width="4.784" x="75.876"><![CDATA[2]]></word><word id="1600100" width="2.8" x="83.452"><![CDATA[•]]></word><word id="1600101" width="35.864" x="89.044"><![CDATA[Historical]]></word><word id="1600102" width="25.656" x="127.7"><![CDATA[Fiction]]></word></line></para><para height="24.391" id="1600012" poly="m 41.8651 37.738625 l 41.8651 62.1294 l 309.78897 62.1294 l 309.78897 37.738625 z" width="267.924" x="41.865" y="37.739"><line height="32.547" id="1600027" y="63.36"><word id="1600103" width="101.887" x="132.12"><![CDATA[SHARED]]></word><word id="1600104" width="67.317" x="244.211"><![CDATA[READ]]></word></line><line height="29.08" id="1600028" y="67.329"><word id="1600105" width="67.227" x="41.865"><![CDATA[Reread]]></word></line></para><para height="4.661" id="1600013" poly="m 47.8692 154.33868 l 47.8692 158.9992 l 94.2207 158.9992 l 94.2207 154.33868 z" width="46.352" x="47.869" y="154.339"><line height="8.047" id="1600029" y="160.644"><word id="1600106" width="47.151" x="47.869"><![CDATA[COLLABORATE]]></word></line></para><para height="5.76" id="1600014" poly="m 621.036 624.24 l 621.036 630.0 l 690.804 630.0 l 690.804 624.24 z" width="69.768" x="621.036" y="624.24"><line height="9.888" id="1600030" y="632"><word id="1600107" width="19.176" x="621.036"><![CDATA[TEKS]]></word><word id="1600108" width="23.672" x="642.684"><![CDATA[3.7(B),]]></word><word id="1600109" width="21.976" x="668.828"><![CDATA[3.7(C)]]></word></line></para></page></pages>