<?xml version="1.0" encoding="UTF-8"?>
<pages><page><para height="21.808" id="1420001" poly="m 102.0 92.02872 l 102.0 113.8367 l 182.707 113.8367 l 182.707 92.02872 z" width="80.707" x="102.0" y="92.029"><line height="34.916" id="1420001" y="121.928"><word id="1420001" width="81.2" x="102"><![CDATA[Revise]]></word></line></para><para height="46.982" id="1420002" poly="m 102.0 132.84995 l 102.0 179.8322 l 519.24 179.8322 l 519.24 132.84995 z" width="417.24" x="102.0" y="132.85"><line height="17.741" id="1420002" y="147.542"><word id="1420002" width="44.474" x="102"><![CDATA[Strong]]></word><word id="1420003" width="71.72" x="151.134"><![CDATA[Conclusion]]></word><word id="1420004" width="17.699" x="229.694"><![CDATA[An]]></word><word id="1420005" width="66.476" x="251.511"><![CDATA[expository]]></word><word id="1420006" width="34.698" x="322.106"><![CDATA[essay]]></word><word id="1420007" width="37.749" x="360.922"><![CDATA[needs]]></word><word id="1420008" width="8.507" x="402.789"><![CDATA[a]]></word><word id="1420009" width="40.342" x="415.414"><![CDATA[strong]]></word></line><line height="16.63" id="1420003" y="165.254"><word id="1420010" width="67.431" x="102"><![CDATA[conclusion]]></word><word id="1420011" width="26.862" x="173.549"><![CDATA[that]]></word><word id="1420012" width="48.664" x="204.529"><![CDATA[stresses]]></word><word id="1420013" width="14.506" x="257.311"><![CDATA[its]]></word><word id="1420014" width="31.578" x="275.936"><![CDATA[most]]></word><word id="1420015" width="64.282" x="311.632"><![CDATA[important]]></word><word id="1420016" width="41.581" x="380.032"><![CDATA[points.]]></word><word id="1420017" width="23.954" x="425.732"><![CDATA[The]]></word><word id="1420018" width="67.431" x="453.804"><![CDATA[conclusion]]></word></line><line height="16.63" id="1420004" y="183.252"><word id="1420019" width="41.809" x="102"><![CDATA[should]]></word><word id="1420020" width="42.65" x="147.928"><![CDATA[repeat]]></word><word id="1420021" width="21.161" x="194.696"><![CDATA[the]]></word><word id="1420022" width="32.504" x="219.976"><![CDATA[main]]></word><word id="1420023" width="27.773" x="256.598"><![CDATA[idea]]></word><word id="1420024" width="12.996" x="288.49"><![CDATA[of]]></word><word id="1420025" width="21.161" x="305.604"><![CDATA[the]]></word><word id="1420026" width="34.699" x="330.883"><![CDATA[essay]]></word><word id="1420027" width="11.785" x="369.7"><![CDATA[in]]></word><word id="1420028" width="8.508" x="385.603"><![CDATA[a]]></word><word id="1420029" width="27.289" x="398.229"><![CDATA[new]]></word><word id="1420030" width="27.673" x="429.636"><![CDATA[way.]]></word></line></para><para height="12.152" id="1420003" poly="m 557.38 95.13406 l 557.38 107.2861 l 609.27795 107.2861 l 609.27795 95.13406 z" width="51.898" x="557.38" y="95.134"><line height="16.856" id="1420005" y="111.192"><word id="1420031" width="32.256" x="557.38"><![CDATA[Quick]]></word><word id="1420032" width="16.576" x="593.304"><![CDATA[Tip]]></word></line></para><para height="104.909" id="1420004" poly="m 553.84 125.16817 l 553.84 230.0772 l 684.37604 230.0772 l 684.37604 125.16817 z" width="130.536" x="553.84" y="125.168"><line height="14.296" id="1420006" y="137.026"><word id="1420033" width="60.331" x="553.84"><![CDATA[Remember]]></word><word id="1420034" width="11.343" x="618.006"><![CDATA[to]]></word><word id="1420035" width="18.547" x="633.183"><![CDATA[use]]></word><word id="1420036" width="30.012" x="655.564"><![CDATA[facts,]]></word></line><line height="14.296" id="1420007" y="153.025"><word id="1420037" width="39.8" x="553.84"><![CDATA[details,]]></word><word id="1420038" width="21.07" x="597.56"><![CDATA[and]]></word><word id="1420039" width="57.097" x="622.55"><![CDATA[definitions]]></word></line><line height="14.296" id="1420008" y="169.023"><word id="1420040" width="39.298" x="553.84"><![CDATA[related]]></word><word id="1420041" width="11.343" x="597.058"><![CDATA[to]]></word><word id="1420042" width="24.255" x="612.321"><![CDATA[your]]></word><word id="1420043" width="27.881" x="640.496"><![CDATA[topic]]></word></line><line height="14.296" id="1420009" y="185.022"><word id="1420044" width="11.343" x="553.84"><![CDATA[to]]></word><word id="1420045" width="22.92" x="569.103"><![CDATA[fully]]></word><word id="1420046" width="40.131" x="595.943"><![CDATA[explain]]></word><word id="1420047" width="24.255" x="639.994"><![CDATA[your]]></word></line><line height="14.296" id="1420010" y="201.02"><word id="1420048" width="31.715" x="553.84"><![CDATA[ideas.]]></word><word id="1420049" width="40.805" x="589.475"><![CDATA[Present]]></word><word id="1420050" width="26.521" x="634.2"><![CDATA[facts]]></word></line><line height="14.296" id="1420011" y="217.019"><word id="1420051" width="21.07" x="553.84"><![CDATA[and]]></word><word id="1420052" width="36.309" x="578.83"><![CDATA[details]]></word><word id="1420053" width="10.02" x="619.059"><![CDATA[in]]></word><word id="1420054" width="7.314" x="632.999"><![CDATA[a]]></word><word id="1420055" width="37.044" x="644.233"><![CDATA[logical]]></word></line><line height="14.296" id="1420012" y="233.017"><word id="1420056" width="31.862" x="553.84"><![CDATA[order.]]></word></line></para><para height="46.982" id="1420005" poly="m 101.9978 194.85175 l 101.9978 241.834 l 525.09454 241.834 l 525.09454 194.85175 z" width="423.097" x="101.998" y="194.852"><line height="16.63" id="1420013" y="209.258"><word id="1420057" width="45.457" x="101.998"><![CDATA[Reread]]></word><word id="1420058" width="21.161" x="151.574"><![CDATA[the]]></word><word id="1420059" width="23.128" x="176.853"><![CDATA[last]]></word><word id="1420060" width="67.887" x="204.099"><![CDATA[paragraph]]></word><word id="1420061" width="30.153" x="276.104"><![CDATA[from]]></word><word id="1420062" width="40.726" x="310.376"><![CDATA["Every]]></word><word id="1420063" width="29.469" x="355.22"><![CDATA[Vote]]></word><word id="1420064" width="53.594" x="388.808"><![CDATA[Counts!"]]></word><word id="1420065" width="16.245" x="446.52"><![CDATA[on]]></word><word id="1420066" width="33.146" x="466.883"><![CDATA[page]]></word><word id="1420067" width="25.707" x="504.147"><![CDATA[108.]]></word></line><line height="16.63" id="1420014" y="227.256"><word id="1420068" width="26.448" x="101.998"><![CDATA[Talk]]></word><word id="1420069" width="28.201" x="132.564"><![CDATA[with]]></word><word id="1420070" width="8.507" x="164.883"><![CDATA[a]]></word><word id="1420071" width="48.635" x="177.509"><![CDATA[partner]]></word><word id="1420072" width="38.076" x="230.262"><![CDATA[about]]></word><word id="1420073" width="26.933" x="272.456"><![CDATA[how]]></word><word id="1420074" width="21.161" x="303.507"><![CDATA[the]]></word><word id="1420075" width="43.12" x="328.787"><![CDATA[author]]></word><word id="1420076" width="29.868" x="376.025"><![CDATA[ends]]></word><word id="1420077" width="21.161" x="410.012"><![CDATA[the]]></word><word id="1420078" width="36.466" x="435.291"><![CDATA[essay.]]></word><word id="1420079" width="37.82" x="475.875"><![CDATA[Write]]></word></line><line height="16.63" id="1420015" y="245.254"><word id="1420080" width="38.076" x="101.998"><![CDATA[about]]></word><word id="1420081" width="11.115" x="144.192"><![CDATA[it.]]></word></line></para><para height="85.722" id="1420006" poly="m 102.083 248.446 l 102.083 334.168 l 530.963 334.168 l 530.963 248.446 z" width="428.88" x="102.083" y="248.446"><line height="16.63" id="1420016" y="275.25"><word id="1420082" width="429.637" x="101.998"><![CDATA[_______________________________________________________]]></word></line><line height="16.63" id="1420017" y="305.246"><word id="1420083" width="429.637" x="101.998"><![CDATA[_______________________________________________________]]></word></line><line height="16.63" id="1420018" y="335.243"><word id="1420084" width="429.637" x="101.998"><![CDATA[_______________________________________________________]]></word></line></para><para height="28.984" id="1420007" poly="m 102.0 353.4561 l 102.0 382.44055 l 530.88226 382.44055 l 530.88226 353.4561 z" width="428.882" x="102.0" y="353.456"><line height="17.741" id="1420019" y="368.148"><word id="1420085" width="42.38" x="102"><![CDATA[Revise]]></word><word id="1420086" width="19.124" x="151.219"><![CDATA[It's]]></word><word id="1420087" width="29.312" x="174.461"><![CDATA[time]]></word><word id="1420088" width="12.967" x="207.892"><![CDATA[to]]></word><word id="1420089" width="36.908" x="224.977"><![CDATA[revise]]></word><word id="1420090" width="27.872" x="266.003"><![CDATA[your]]></word><word id="1420091" width="48.721" x="297.993"><![CDATA[writing.]]></word><word id="1420092" width="32.775" x="350.832"><![CDATA[Read]]></word><word id="1420093" width="27.875" x="387.725"><![CDATA[your]]></word><word id="1420094" width="31.435" x="419.718"><![CDATA[draft]]></word><word id="1420095" width="24.666" x="455.272"><![CDATA[and]]></word><word id="1420096" width="26.775" x="484.057"><![CDATA[look]]></word><word id="1420097" width="17.527" x="514.951"><![CDATA[for]]></word></line><line height="16.63" id="1420020" y="385.861"><word id="1420098" width="40.798" x="102"><![CDATA[places]]></word><word id="1420099" width="39.971" x="146.916"><![CDATA[where]]></word><word id="1420100" width="22.5" x="191.006"><![CDATA[you]]></word><word id="1420101" width="37.179" x="217.624"><![CDATA[might]]></word></line></para><para height="2.992" id="1420008" poly="m 119.99775 406.4518 l 119.99775 409.4443 l 123.1185 409.4443 l 123.1185 406.4518 z" width="3.121" x="119.998" y="406.452"><line height="16.63" id="1420021" y="412.864"><word id="1420102" width="4.987" x="119.998"><![CDATA[•]]></word><word id="1420103" width="25.835" x="132.68"><![CDATA[add]]></word><word id="1420104" width="34.642" x="163.488"><![CDATA[more]]></word><word id="1420105" width="44.674" x="203.103"><![CDATA[details]]></word><word id="1420106" width="28.144" x="252.75"><![CDATA[that]]></word><word id="1420107" width="51.813" x="285.867"><![CDATA[support]]></word><word id="1420108" width="22.017" x="342.653"><![CDATA[the]]></word><word id="1420109" width="33.673" x="369.643"><![CDATA[topic]]></word></line></para><para height="2.992" id="1420009" poly="m 119.9971 433.45557 l 119.9971 436.44806 l 123.11785 436.44806 l 123.11785 433.45557 z" width="3.121" x="119.997" y="433.456"><line height="16.63" id="1420022" y="439.868"><word id="1420110" width="4.988" x="119.997"><![CDATA[•]]></word><word id="1420111" width="36.579" x="132.68"><![CDATA[make]]></word><word id="1420112" width="29.155" x="174.233"><![CDATA[your]]></word><word id="1420113" width="71.279" x="208.361"><![CDATA[conclusion]]></word><word id="1420114" width="56.585" x="284.613"><![CDATA[stronger]]></word></line></para><para height="28.984" id="1420010" poly="m 101.99935 451.4623 l 101.99935 480.4468 l 504.46497 480.4468 l 504.46497 451.4623 z" width="402.466" x="101.999" y="451.462"><line height="16.63" id="1420023" y="465.874"><word id="1420115" width="36.58" x="101.999"><![CDATA[Circle]]></word><word id="1420116" width="24.623" x="143.139"><![CDATA[two]]></word><word id="1420117" width="62.818" x="172.322"><![CDATA[sentences]]></word><word id="1420118" width="11.642" x="239.7"><![CDATA[in]]></word><word id="1420119" width="28.201" x="255.902"><![CDATA[your]]></word><word id="1420120" width="31.863" x="288.663"><![CDATA[draft]]></word><word id="1420121" width="26.263" x="325.086"><![CDATA[that]]></word><word id="1420122" width="22.786" x="355.909"><![CDATA[you]]></word><word id="1420123" width="23.541" x="383.254"><![CDATA[can]]></word><word id="1420124" width="50.431" x="411.355"><![CDATA[change.]]></word><word id="1420125" width="39.487" x="466.346"><![CDATA[Revise]]></word></line><line height="16.63" id="1420024" y="483.867"><word id="1420126" width="24.496" x="102.002"><![CDATA[and]]></word><word id="1420127" width="32.775" x="131.058"><![CDATA[write]]></word><word id="1420128" width="33.302" x="168.393"><![CDATA[them]]></word><word id="1420129" width="31.849" x="206.255"><![CDATA[here.]]></word></line></para><para height="81.919" id="1420011" poly="m 101.796 492.019 l 101.796 573.9376 l 530.676 573.9376 l 530.676 492.019 z" width="428.88" x="101.796" y="492.019"><line height="16.63" id="1420025" y="513.863"><word id="1420130" width="429.638" x="101.988"><![CDATA[_______________________________________________________]]></word></line><line height="16.63" id="1420026" y="543.859"><word id="1420131" width="429.638" x="101.988"><![CDATA[_______________________________________________________]]></word></line><line height="16.63" id="1420027" y="573.856"><word id="1420132" width="429.638" x="101.988"><![CDATA[_______________________________________________________]]></word></line></para><para height="8.211" id="1420012" poly="m 22.0 621.789 l 22.0 630.0 l 38.146 630.0 l 38.146 621.789 z" width="16.146" x="22.0" y="621.789"><line height="13.42" id="1420028" y="632.76"><word id="1420133" width="17.848" x="22"><![CDATA[132]]></word><word id="1420134" width="15.584" x="57.5"><![CDATA[Unit]]></word><word id="1420135" width="4.784" x="75.876"><![CDATA[2]]></word><word id="1420136" width="2.8" x="83.452"><![CDATA[•]]></word><word id="1420137" width="39.424" x="89.044"><![CDATA[Expository]]></word><word id="1420138" width="16.176" x="131.26"><![CDATA[Text]]></word></line></para><para height="20.463" id="1420013" poly="m 35.6 36.517487 l 35.6 56.9805 l 140.02399 56.9805 l 140.02399 36.517487 z" width="104.424" x="35.6" y="36.517"><line height="32.547" id="1420029" y="62.453"><word id="1420139" width="105.849" x="35.6"><![CDATA[WRITING]]></word></line></para><para height="4.66" id="1420014" poly="m 45.4692 218.23871 l 45.4692 222.8992 l 91.8207 222.8992 l 91.8207 218.23871 z" width="46.351" x="45.469" y="218.239"><line height="8.047" id="1420030" y="224.544"><word id="1420140" width="47.151" x="45.469"><![CDATA[COLLABORATE]]></word></line></para><para height="5.76" id="1420015" poly="m 616.228 624.24 l 616.228 630.0 l 690.004 630.0 l 690.004 624.24 z" width="73.776" x="616.228" y="624.24"><line height="9.888" id="1420031" y="632"><word id="1420141" width="19.176" x="616.228"><![CDATA[TEKS]]></word><word id="1420142" width="25.376" x="637.876"><![CDATA[3.11(C),]]></word><word id="1420143" width="24.28" x="665.724"><![CDATA[3.12(B)]]></word></line></para><para height="69.173" id="1420016" poly="m 26.5 540.827 l 26.5 610.0 l 27.255001 610.0 l 27.255001 540.827 z" width="0.755" x="26.5" y="540.827"><line height="66.54" id="1420032" y="611.452"><word id="1420144" width="2.676" x="26.5"><![CDATA[S]]></word><word id="1420145" width="1.848" x="26.5"><![CDATA[t]]></word><word id="1420146" width="2.754" x="26.5"><![CDATA[e]]></word><word id="1420147" width="2.436" x="26.5"><![CDATA[v]]></word><word id="1420148" width="2.754" x="26.5"><![CDATA[e]]></word><word id="1420149" width="3.318" x="26.5"><![CDATA[D]]></word><word id="1420150" width="2.754" x="26.5"><![CDATA[e]]></word><word id="1420151" width="2.958" x="26.5"><![CDATA[b]]></word><word id="1420152" width="2.754" x="26.5"><![CDATA[e]]></word><word id="1420153" width="2.718" x="26.5"><![CDATA[n]]></word><word id="1420154" width="2.904" x="26.5"><![CDATA[p]]></word><word id="1420155" width="2.832" x="26.5"><![CDATA[o]]></word><word id="1420156" width="1.908" x="26.5"><![CDATA[r]]></word><word id="1420157" width="1.848" x="26.5"><![CDATA[t]]></word><word id="1420158" width="2.346" x="26.5"><![CDATA[/]]></word><word id="1420159" width="3.408" x="26.5"><![CDATA[G]]></word><word id="1420160" width="2.754" x="26.5"><![CDATA[e]]></word><word id="1420161" width="1.848" x="26.5"><![CDATA[t]]></word><word id="1420162" width="1.848" x="26.5"><![CDATA[t]]></word><word id="1420163" width="2.448" x="26.5"><![CDATA[y]]></word><word id="1420164" width="2.064" x="26.5"><![CDATA[I]]></word><word id="1420165" width="4.206" x="26.5"><![CDATA[m]]></word><word id="1420166" width="2.898" x="26.5"><![CDATA[a]]></word><word id="1420167" width="2.904" x="26.5"><![CDATA[g]]></word><word id="1420168" width="2.754" x="26.5"><![CDATA[e]]></word><word id="1420169" width="2.016" x="26.5"><![CDATA[s]]></word></line></para></page></pages>